davincirunsdk/__init__.py
davincirunsdk/common.py
davincirunsdk/davincirun.py
davincirunsdk/fmk.py
davincirunsdk/manager.py
davincirunsdk/rank_table.py
davincirunsdk/sdr.py
davincirunsdk/split_log.py
davincirunsdk/upload_tail_log.py
davincirunsdk/notebook/__init__.py
davincirunsdk/notebook/cli.py
davincirunsdk/notebook/exception.py
davincirunsdk/notebook/fmk.py
davincirunsdk/notebook/manager.py
davincirunsdk/notebook/sdk.py
davincirunsdk/notebook/tailer.py
davincirunsdk/notebook/utils.py
davincirunsdk-0.1.5.dist-info/LICENSE
davincirunsdk-0.1.5.dist-info/METADATA
davincirunsdk-0.1.5.dist-info/WHEEL
davincirunsdk-0.1.5.dist-info/entry_points.txt
davincirunsdk-0.1.5.dist-info/top_level.txt
davincirunsdk-0.1.5.dist-info/RECORD
