Metadata-Version: 2.1
Name: davincirunsdk
Version: 0.1.5
Summary: davincirunsdk
Home-page: https://github.com/Wh1isper/davincirunsdk
Author: Wh1isper
Author-email: 9573586@qq.com
License: MIT
Platform: UNKNOWN
Classifier: Development Status :: 3 - Alpha
Classifier: Intended Audience :: Developers
Classifier: Programming Language :: Python :: 3
Classifier: Programming Language :: Python :: 3.5
Classifier: Programming Language :: Python :: 3.6
Classifier: Programming Language :: Python :: 3.7
Classifier: Programming Language :: Python :: 3.8
Classifier: License :: OSI Approved :: MIT License
License-File: LICENSE
Requires-Dist: sh
